ilayoutx/__init__.py
ilayoutx/_ilayoutx.cpython-311-darwin.so
ilayoutx/experimental/__init__.py
ilayoutx/experimental/layouts/__init__.py
ilayoutx/experimental/packing/__init__.py
ilayoutx/experimental/utils.py
ilayoutx/external/netgraph/geometric.py
ilayoutx/external/networkx/arf.py
ilayoutx/external/networkx/forceatlas2.py
ilayoutx/external/networkx/kamada_kawai.py
ilayoutx/external/networkx/spring.py
ilayoutx/external/numba/__init__.py
ilayoutx/external/umap/__init__.py
ilayoutx/ingest/__init__.py
ilayoutx/ingest/providers/igraph.py
ilayoutx/ingest/providers/networkx.py
ilayoutx/ingest/typing.py
ilayoutx/layouts/__init__.py
ilayoutx/layouts/arf_layouts.py
ilayoutx/layouts/basic_layouts.py
ilayoutx/layouts/bipartite_layouts.py
ilayoutx/layouts/forceatlas2_layouts.py
ilayoutx/layouts/gem_layouts.py
ilayoutx/layouts/geometric_layouts.py
ilayoutx/layouts/grid_layouts.py
ilayoutx/layouts/kamada_kawai_layouts.py
ilayoutx/layouts/lgl_layouts.py
ilayoutx/layouts/mds_layouts.py
ilayoutx/layouts/multipartite_layouts.py
ilayoutx/layouts/spring_layouts.py
ilayoutx/layouts/sugiyama_layouts.py
ilayoutx/layouts/umap_layouts.py
ilayoutx/packing/__init__.py
ilayoutx/packing/circular.py
ilayoutx/packing/rectangular.py
ilayoutx/routing/__init__.py
ilayoutx/utils.py
ilayoutx-0.3.0.dist-info/METADATA
ilayoutx-0.3.0.dist-info/WHEEL
ilayoutx-0.3.0.dist-info/RECORD
