Metadata-Version: 2.4
Name: ilayoutx
Version: 0.3.0
Classifier: Development Status :: 3 - Alpha
Classifier: Programming Language :: Python :: Implementation :: CPython
Classifier: Programming Language :: Python :: Implementation :: PyPy
Classifier: Programming Language :: Python :: 3.11
Classifier: Programming Language :: Python :: 3.12
Classifier: Programming Language :: Python :: 3.13
Classifier: Programming Language :: Python :: 3.14
Classifier: Programming Language :: Python :: 3 :: Only
Classifier: Programming Language :: Rust
Classifier: License :: OSI Approved :: MIT License
Classifier: Intended Audience :: Developers
Classifier: Intended Audience :: Education
Classifier: Intended Audience :: Science/Research
Classifier: Natural Language :: English
Classifier: Topic :: Scientific/Engineering
Classifier: Topic :: Scientific/Engineering :: Information Analysis
Classifier: Topic :: Scientific/Engineering :: Mathematics
Classifier: Topic :: Scientific/Engineering :: Physics
Classifier: Topic :: Scientific/Engineering :: Bio-Informatics
Classifier: Topic :: Scientific/Engineering :: Visualization
Classifier: Topic :: Software Development :: Libraries :: Python Modules
Classifier: Typing :: Typed
Requires-Dist: numpy>=2.0.0
Requires-Dist: pandas>=2.0.0
Requires-Dist: scipy>=1.11.0
Requires-Dist: rectangle-packer>=2.0.0
Requires-Dist: circlify>=0.15.0
Requires-Dist: ilayoutx[fastmath,plot] ; extra == 'all'
Requires-Dist: numba>=0.63.1 ; extra == 'fastmath'
Requires-Dist: matplotlib>=3.10.0 ; extra == 'plot'
Requires-Dist: iplotx>=1.6.0 ; extra == 'plot'
Provides-Extra: all
Provides-Extra: fastmath
Provides-Extra: plot
Summary: Universal library for network node layout and edge routing.
Keywords: network,graph,layout,routing,embedding
Author-email: Fabio Zanini <fabio.zanini@unsw.edu.au>
Maintainer-email: Fabio Zanini <fabio.zanini@unsw.edu.au>
License: MIT
Requires-Python: >=3.11
Project-URL: Bug Tracker, https://github.com/fabilab/ilayoutx/issues
Project-URL: Changelog, https://github.com/fabilab/ilayoutx/blob/main/CHANGELOG.md
Project-URL: Documentation, https://readthedocs.org/ilayoutx
Project-URL: Homepage, https://github.com/fabilab/ilayoutx
Project-URL: Repository, https://github.com/fabilab/ilayoutx.git
